setup.py
icy/__init__.py
icy/icy.py
icy/utils.py
icy.egg-info/PKG-INFO
icy.egg-info/SOURCES.txt
icy.egg-info/dependency_links.txt
icy.egg-info/pbr.json
icy.egg-info/requires.txt
icy.egg-info/top_level.txt
icy/ext/__init__.py
icy/ext/xml2json.py
icy/ml/__init__.py
icy/ml/crossval.py
icy/ml/explore.py
icy/ml/features.py
icy/ml/metrics.py
icy/ml/persist.py
icy/ml/prep.py