Metadata-Version: 1.1
Name: icy
Version: 0.0.16
Summary: data wrangling glue code
Home-page: https://github.com/rcs-analytics/icy
Author: Jonathan Rahn
Author-email: jr@rcs-analytics.com
License: MIT
Platform: any
Classifier: Development Status :: 3 - Alpha
Classifier: Environment :: Console
Classifier: Intended Audience :: Science/Research
Classifier: License :: OSI Approved :: MIT License
Classifier: Programming Language :: Python
Classifier: Programming Language :: Python :: 3
Classifier: Programming Language :: Python :: 3.4
Classifier: Programming Language :: Python :: 3.5
Classifier: Programming Language :: Python :: 3 :: Only
Classifier: Topic :: Scientific/Engineering
Classifier: Topic :: Software Development :: Libraries :: Python Modules
